exedra/__init__.py
exedra-0.0.1.dist-info/LICENSE
exedra-0.0.1.dist-info/WHEEL
exedra-0.0.1.dist-info/METADATA
exedra-0.0.1.dist-info/RECORD
