Metadata-Version: 2.1
Name: exedra
Version: 0.0.1
Summary: Exedra is a unified programming model for composable ML pipelines.
Author-email: Deepyaman Datta <deepyaman.datta@utexas.edu>
Classifier: License :: OSI Approved :: MIT License
Project-URL: Home, https://github.com/deepyaman/exedra
